CHANGELOG.rst
MANIFEST.in
README.rst
setup.py
django_future_url/__init__.py
django_future_url/core.py
django_future_url.egg-info/PKG-INFO
django_future_url.egg-info/SOURCES.txt
django_future_url.egg-info/dependency_links.txt
django_future_url.egg-info/requires.txt
django_future_url.egg-info/top_level.txt
django_future_url/bin/future_url
django_future_url/test/__init__.py
django_future_url/test/test_core.py