Metadata-Version: 1.0
Name: django-future-url
Version: 0.2.2
Summary: Migration tool for django 1.4, fixes url template tag deprecation warnings.
Home-page: https://github.com/futurecolors/django-future-url/
Author: Vitaly Olevinsky
Author-email: olevinsky.v.s@gmail.com
License: MIT
Platform: UNKNOWN
Classifier: Development Status :: 4 - Beta
Classifier: Framework :: Django
Classifier: Intended Audience :: Developers
Classifier: License :: OSI Approved :: MIT License
Classifier: Operating System :: OS Independent
Classifier: Programming Language :: Python
Classifier: Programming Language :: Python :: 2.6
Classifier: Programming Language :: Python :: 2.7
Classifier: Programming Language :: Python :: 3.2
Classifier: Programming Language :: Python :: 3.3
